LICENSE
README.md
setup.cfg
setup.py
airfoil_generator/__init__.py
airfoil_generator/cst.py
airfoil_generator/database.py
airfoil_generator/geometry.py
airfoil_generator/naca.py
airfoil_generator/utils.py
airfoil_generator.egg-info/PKG-INFO
airfoil_generator.egg-info/SOURCES.txt
airfoil_generator.egg-info/dependency_links.txt
airfoil_generator.egg-info/requires.txt
airfoil_generator.egg-info/top_level.txt
airfoil_generator/airfoil_database/2032c.dat
airfoil_generator/airfoil_database/__init__.py
airfoil_generator/airfoil_database/a18.dat
airfoil_generator/airfoil_database/a18sm.dat
airfoil_generator/airfoil_database/a63a108c.dat
airfoil_generator/airfoil_database/ag03.dat
airfoil_generator/airfoil_database/ag04.dat
airfoil_generator/airfoil_database/ag08.dat
airfoil_generator/airfoil_database/ag09.dat
airfoil_generator/airfoil_database/ag10.dat
airfoil_generator/airfoil_database/ag11.dat
airfoil_generator/airfoil_database/ag12.dat
airfoil_generator/airfoil_database/ag13.dat
airfoil_generator/airfoil_database/ag14.dat
airfoil_generator/airfoil_database/ag16.dat
airfoil_generator/airfoil_database/ag17.dat
airfoil_generator/airfoil_database/ag18.dat
airfoil_generator/airfoil_database/ag19.dat
airfoil_generator/airfoil_database/ag23.dat
airfoil_generator/airfoil_database/ag24.dat
airfoil_generator/airfoil_database/ag25.dat
airfoil_generator/airfoil_database/ag26.dat
airfoil_generator/airfoil_database/ag27.dat
airfoil_generator/airfoil_database/ag34.dat
airfoil_generator/airfoil_database/ag35.dat
airfoil_generator/airfoil_database/ag36.dat
airfoil_generator/airfoil_database/ag37.dat
airfoil_generator/airfoil_database/ag38.dat
airfoil_generator/airfoil_database/ag40d-02r.dat
airfoil_generator/airfoil_database/ag41d-02r.dat
airfoil_generator/airfoil_database/ag42d-02r.dat
airfoil_generator/airfoil_database/ag43d-02r.dat
airfoil_generator/airfoil_database/ag44ct-02r.dat
airfoil_generator/airfoil_database/ag44ct02r.dat
airfoil_generator/airfoil_database/ag455ct-02r.dat
airfoil_generator/airfoil_database/ag455ct02r.dat
airfoil_generator/airfoil_database/ag45c-03.dat
airfoil_generator/airfoil_database/ag45c03.dat
airfoil_generator/airfoil_database/ag45ct-02r.dat
