Metadata-Version: 2.1
Name: airfoil-generator
Version: 0.1.5
Summary: Airfoil data points generator with multiple methods.
Home-page: https://github.com/open-foil
Download-URL: https://github.com/open-foil/airfoil-generator/archive/refs/tags/v0.1.5.tar.gz
Author: OpenFoil
Author-email: openfoil.project@gmail.com
License: MIT
Keywords: airfoil,generator,aerodynamics,naca,cst
Classifier: Development Status :: 3 - Alpha
Classifier: Intended Audience :: Developers
Classifier: Topic :: Software Development :: Build Tools
Classifier: License :: OSI Approved :: MIT License
Classifier: Programming Language :: Python :: 3
Classifier: Programming Language :: Python :: 3.9
Classifier: Programming Language :: Python :: 3.10
Classifier: Programming Language :: Python :: 3.11
License-File: LICENSE
